sequence-detector-moore-DE10-Lite/seq_rec.vhd
--Sequence Recognizer: VHDL Process Description
library ieee;
use ieee.std_logic_1164.all;

entity seq_rec is
   port (
      CLK, RESET, X : in std_logic;
      Z             : out std_logic
   );
end seq_rec;

architecture process_3 of seq_rec is
   type state_type is (A, B, C, D, E);
   signal state, next_state : state_type;
begin

   -- Process 1: State register with asynchronous reset
   state_register: process (CLK, RESET)
   begin
      if (RESET = '1') then
         state <= A;
      elsif (CLK'event and CLK = '1') then
         state <= next_state;
      end if;
   end process;

   -- Process 2: Next state logic
   next_state_func: process (X, state)
   begin
      case state is
         when A =>
            if X = '1' then
               next_state <= B;
            else
               next_state <= A;
            end if;
         when B =>
            if X = '1' then
               next_state <= C;
            else
               next_state <= A;
            end if;
         when C =>
            if X = '1' then
               next_state <= C;
            else
               next_state <= D;
            end if;
         when D =>
            if X = '1' then
               next_state <= E;
            else
               next_state <= A;
            end if;
         when E =>
            if X = '1' then
               next_state <= C;
            else
               next_state <= A;
            end if;
      end case;
   end process;

   -- Process 3: Output logic
   output_func: process (X, state)
   begin
      case state is
         when E =>
            Z <= '1';
         when others =>
            Z <= '0';
      end case;
   end process;

end process_3;

intro-vhdl/seq_rec_testbench.vhd
-- Testbench for seq_rec - Sequence Detector
library ieee;
use ieee.std_logic_1164.all;

entity seq_rec_testbench is
end seq_rec_testbench;

architecture tb_arch of seq_rec_testbench is
   signal CLK, RESET, X : std_logic;
   signal Z : std_logic;
begin

   -- Instantiate the Unit Under Test (UUT)
   uut: entity work.seq_rec(process_3)
      port map (
         CLK => CLK,
         RESET => RESET,
         X => X,
         Z => Z
      );

   -- Clock process: 20 ns period (10 ns high, 10 ns low)
   clk_process: process
   begin
      CLK <= '0';
      wait for 10 ns;
      CLK <= '1';
      wait for 10 ns;
   end process;

   -- Stimulus process: generates test vectors
   stimulus_process: process
   begin
      -- Initialize
      RESET <= '1';
      X <= '0';
      wait for 25 ns;

      RESET <= '0';  -- Deassert reset
      
      -- Send bit sequence: 1 1 0 1 -> should detect 1101 → Z='1'
      X <= '1'; wait for 20 ns;  -- First 1
      X <= '1'; wait for 20 ns;  -- Second 1
      X <= '0'; wait for 20 ns;  -- Zero
      X <= '1'; wait for 20 ns;  -- Final 1 (should trigger Z='1')

      -- Another sequence: 1 1 0 1 again (overlapping)
      X <= '1'; wait for 20 ns;
      X <= '1'; wait for 20 ns;
      X <= '0'; wait for 20 ns;
      X <= '1'; wait for 20 ns;

      -- Send a false pattern: 1 0 1 1 (should NOT trigger Z='1')
      X <= '1'; wait for 20 ns;
      X <= '0'; wait for 20 ns;
      X <= '1'; wait for 20 ns;
      X <= '1'; wait for 20 ns;
      wait;
   end process;

end tb_arch;

resposta.vcd
$date
  Sun Jul 27 17:55:49 2025
$end
$version
  GHDL v0
$end
$timescale
  1 fs
$end
$scope module standard $end
$upscope $end
$scope module std_logic_1164 $end
$upscope $end
$scope module seq_rec_testbench $end
$var reg 1 ! clk $end
$var reg 1 " reset $end
$var reg 1 # x $end
$var reg 1 $ z $end
$scope module uut $end
$var reg 1 % clk $end
$var reg 1 & reset $end
$var reg 1 ' x $end
$var reg 1 ( z $end
$comment state is not handled $end
$comment next_state is not handled $end
$upscope $end
$upscope $end
$enddefinitions $end
#0
0!
1"
0#
0$
0%
1&
0'
0(
#10000000
1!
1%
#20000000
0!
0%
#25000000
0"
1#
0&
1'
#30000000
1!
1%
#40000000
0!
0%
#45000000
#50000000
1!
1%
#60000000
0!
0%
#65000000
0#
0'
#70000000
1!
1%
#80000000
0!
0%
#85000000
1#
1$
1'
1(
#90000000
1!
0$
1%
0(
#100000000
0!
0%
#105000000
#110000000
1!
1%
#120000000
0!
0%
#125000000
#130000000
1!
1%
#140000000
0!
0%
#145000000
0#
0'
#150000000
1!
1%
#160000000
0!
0%
#165000000
1#
1$
1'
1(
#170000000
1!
0$
1%
0(
#180000000
0!
0%
#185000000
#190000000
1!
1%
#200000000
0!
0%
#205000000
0#
0'
#210000000
1!
1%
#220000000
0!
0%
#225000000
1#
1$
1'
1(
#230000000
1!
0$
1%
0(
